{
  "salas": [
    {
      "id": 1,
      "nome": "Loja 01 - Prime",
      "andar": "TÉRREO",
      "tamanho": 45,
      "descricao": "Ampla vitrine com pé-direito duplo, localizada estrategicamente próxima à entrada principal para máximo fluxo de pedestres.",
      "imagem_principal": "fotos_predio/foto_predio_1.jpg",
      "fotos": [
        "fotos_predio/foto_predio_1.jpg"
      ],
      "sobre": "Sobre esta Sala",
      "caracteristicas": [
        "Piso em porcelanato de alta qualidade",
        "Pintura em tons neutros e sofisticados",
        "Iluminação LED com controle de intensidade",
        "Tomadas e pontos de dados estrategicamente distribuídos",
        "Divisórias móveis para flexibilidade de layout",
        "Acabamento premium em todos os detalhes"
      ],
      "specs": [
        {
          "icon": "📏",
          "titulo": "Tamanho",
          "valor": "45 m²"
        },
        {
          "icon": "❄️",
          "titulo": "Climatização",
          "valor": "Ar-condicionado central"
        },
        {
          "icon": "⚡",
          "titulo": "Infraestrutura",
          "valor": "Internet de alta velocidade"
        },
        {
          "icon": "🔒",
          "titulo": "Segurança",
          "valor": "Vigilância 24/7"
        },
        {
          "icon": "🚪",
          "titulo": "Entrada",
          "valor": "Independente"
        },
        {
          "icon": "🅿️",
          "titulo": "Estacionamento",
          "valor": "Incluído"
        }
      ],
      "facilidades": [
        {
          "icon": "🅿️",
          "valor": "Estacionamento"
        },
        {
          "icon": "🛗",
          "valor": "Elevador moderno e rápido"
        },
        {
          "icon": "🏢",
          "valor": "Portaria"
        },
        {
          "icon": "🎯",
          "valor": "Localização estratégica"
        }
      ],
      "alugada": false,
      "inativa": false,
      "data_aluguel": null,
      "motivo_inativa": "",
      "destaque": false
    },
    {
      "id": 2,
      "nome": "Sala 204 - Executive",
      "andar": "SEGUNDO ANDAR",
      "tamanho": 32,
      "descricao": "Unidade silenciosa com vista privilegiada para o jardim interno. Ideal para consultórios ou escritórios de advocacia. Este espaço oferece o conforto e a privacidade necessários para seu negócio prosperar.",
      "imagem_principal": "fotos_predio/foto_predio_2.jpg",
      "fotos": [
        "fotos_predio/foto_predio_2.jpg"
      ],
      "sobre": "Sobre esta Sala",
      "caracteristicas": [
        "Piso em porcelanato de alta qualidade",
        "Pintura em tons neutros e sofisticados",
        "Iluminação LED com controle de intensidade",
        "Tomadas e pontos de dados estrategicamente distribuídos",
        "Divisórias móveis para flexibilidade de layout",
        "Acabamento premium em todos os detalhes"
      ],
      "specs": [
        {
          "icon": "📏",
          "titulo": "Tamanho",
          "valor": "32 m²"
        },
        {
          "icon": "❄️",
          "titulo": "Climatização",
          "valor": "Ar-condicionado individual"
        },
        {
          "icon": "⚡",
          "titulo": "Infraestrutura",
          "valor": "Internet de alta velocidade"
        },
        {
          "icon": "🔒",
          "titulo": "Segurança",
          "valor": "Vigilância 24/7"
        },
        {
          "icon": "🚪",
          "titulo": "Entrada",
          "valor": "Compartilhada"
        },
        {
          "icon": "🅿️",
          "titulo": "Estacionamento",
          "valor": "Incluído"
        }
      ],
      "facilidades": [
        {
          "icon": "🅿️",
          "valor": "Estacionamento"
        },
        {
          "icon": "🛗",
          "valor": "Elevador moderno e rápido"
        },
        {
          "icon": "🏢",
          "valor": "Portaria"
        },
        {
          "icon": "🎯",
          "valor": "Localização estratégica"
        }
      ],
      "alugada": false,
      "inativa": false,
      "data_aluguel": null,
      "motivo_inativa": "",
      "destaque": false
    },
    {
      "id": 3,
      "nome": "Sala 112 - Corporativa",
      "andar": "PRIMEIRO ANDAR",
      "tamanho": 58,
      "descricao": "Espaço modular que permite personalização total do layout. Perfeito para startups e times em crescimento.",
      "imagem_principal": "fotos_predio/foto_predio_3.jpg",
      "fotos": [
        "fotos_predio/foto_predio_3.jpg"
      ],
      "sobre": "Sobre esta Sala",
      "caracteristicas": [
        "Piso em porcelanato de alta qualidade",
        "Pintura em tons neutros e sofisticados",
        "Iluminação LED com controle de intensidade",
        "Tomadas e pontos de dados estrategicamente distribuídos",
        "Divisórias móveis para flexibilidade de layout",
        "Acabamento premium em todos os detalhes"
      ],
      "specs": [
        {
          "icon": "📏",
          "titulo": "Tamanho",
          "valor": "58 m²"
        },
        {
          "icon": "❄️",
          "titulo": "Climatização",
          "valor": "Ar-condicionado central"
        },
        {
          "icon": "⚡",
          "titulo": "Infraestrutura",
          "valor": "Internet de alta velocidade"
        },
        {
          "icon": "🔒",
          "titulo": "Segurança",
          "valor": "Vigilância 24/7"
        },
        {
          "icon": "🚪",
          "titulo": "Entrada",
          "valor": "Independente"
        },
        {
          "icon": "🅿️",
          "titulo": "Estacionamento",
          "valor": "Incluído"
        }
      ],
      "facilidades": [
        {
          "icon": "🅿️",
          "valor": "Estacionamento"
        },
        {
          "icon": "🛗",
          "valor": "Elevador moderno e rápido"
        },
        {
          "icon": "🏢",
          "valor": "Portaria"
        },
        {
          "icon": "🎯",
          "valor": "Localização estratégica"
        }
      ],
      "alugada": false,
      "inativa": false,
      "data_aluguel": null,
      "motivo_inativa": "",
      "destaque": false
    },
    {
      "id": 4,
      "nome": "Loja 05 - Hub Criativo",
      "andar": "SUBSOLO",
      "tamanho": 74,
      "descricao": "Acesso facilitado pelo estacionamento e elevadores. Excelente para estúdios, gráficas ou serviços técnicos.",
      "imagem_principal": "fotos_predio/foto_predio_4.jpg",
      "fotos": [
        "fotos_predio/foto_predio_4.jpg"
      ],
      "sobre": "Sobre esta Sala",
      "caracteristicas": [
        "Piso em porcelanato de alta qualidade",
        "Pintura em tons neutros e sofisticados",
        "Iluminação LED com controle de intensidade",
        "Tomadas e pontos de dados estrategicamente distribuídos",
        "Divisórias móveis para flexibilidade de layout",
        "Acabamento premium em todos os detalhes"
      ],
      "specs": [
        {
          "icon": "📏",
          "titulo": "Tamanho",
          "valor": "74 m²"
        },
        {
          "icon": "❄️",
          "titulo": "Climatização",
          "valor": "Ar-condicionado central"
        },
        {
          "icon": "⚡",
          "titulo": "Infraestrutura",
          "valor": "Internet de alta velocidade"
        },
        {
          "icon": "🔒",
          "titulo": "Segurança",
          "valor": "Vigilância 24/7"
        },
        {
          "icon": "🚪",
          "titulo": "Entrada",
          "valor": "Independente"
        },
        {
          "icon": "🅿️",
          "titulo": "Estacionamento",
          "valor": "Incluído"
        }
      ],
      "facilidades": [
        {
          "icon": "🅿️",
          "valor": "Estacionamento"
        },
        {
          "icon": "🛗",
          "valor": "Elevador moderno e rápido"
        },
        {
          "icon": "🏢",
          "valor": "Portaria"
        },
        {
          "icon": "🎯",
          "valor": "Localização estratégica"
        }
      ],
      "alugada": false,
      "inativa": false,
      "data_aluguel": null,
      "motivo_inativa": "",
      "destaque": false
    },
    {
      "id": 5,
      "nome": "Sala 301 - Premium",
      "andar": "SEGUNDO ANDAR",
      "tamanho": 42,
      "descricao": "Sala de reuniões com equipamentos de videoconferência. Perfeita para apresentações e eventos corporativos.",
      "imagem_principal": "fotos_predio/foto_predio_5.jpg",
      "fotos": [
        "fotos_predio/foto_predio_5.jpg"
      ],
      "sobre": "Sobre esta Sala",
      "caracteristicas": [
        "Piso em porcelanato de alta qualidade",
        "Pintura em tons neutros e sofisticados",
        "Iluminação LED com controle de intensidade",
        "Tomadas e pontos de dados estrategicamente distribuídos",
        "Divisórias móveis para flexibilidade de layout",
        "Acabamento premium em todos os detalhes"
      ],
      "specs": [
        {
          "icon": "📏",
          "titulo": "Tamanho",
          "valor": "42 m²"
        },
        {
          "icon": "❄️",
          "titulo": "Climatização",
          "valor": "Ar-condicionado individual"
        },
        {
          "icon": "⚡",
          "titulo": "Infraestrutura",
          "valor": "Internet de alta velocidade"
        },
        {
          "icon": "🔒",
          "titulo": "Segurança",
          "valor": "Vigilância 24/7"
        },
        {
          "icon": "🚪",
          "titulo": "Entrada",
          "valor": "Compartilhada"
        },
        {
          "icon": "🅿️",
          "titulo": "Estacionamento",
          "valor": "Incluído"
        }
      ],
      "facilidades": [
        {
          "icon": "🅿️",
          "valor": "Estacionamento"
        },
        {
          "icon": "🛗",
          "valor": "Elevador moderno e rápido"
        },
        {
          "icon": "🏢",
          "valor": "Portaria"
        },
        {
          "icon": "🎯",
          "valor": "Localização estratégica"
        }
      ],
      "alugada": false,
      "inativa": false,
      "data_aluguel": null,
      "motivo_inativa": "",
      "destaque": false
    },
    {
      "id": 6,
      "nome": "Loja 02 - Commerce",
      "andar": "SEGUNDO ANDAR",
      "tamanho": 36,
      "descricao": "Unidade silenciosa com vista privilegiada para o jardim interno. Ideal para consultórios ou escritórios de advocacia. Este espaço oferece o conforto e a privacidade necessários para seu negócio prosperar.",
      "imagem_principal": "sala_3/foto_sala_3_1.jpg",
      "fotos": [
        "sala_3/foto_sala_3_1.jpg",
        "sala_3/foto_sala_3_2.jpg",
        "sala_3/foto_sala_3_3.jpg"
      ],
      "sobre": "Sobre esta Sala",
      "caracteristicas": [
        "Piso em porcelanato de alta qualidade",
        "Pintura em tons neutros e sofisticados",
        "Iluminação LED com controle de intensidade",
        "Tomadas e pontos de dados estrategicamente distribuídos",
        "Divisórias móveis para flexibilidade de layout",
        "Acabamento premium em todos os detalhes"
      ],
      "specs": [
        {
          "icon": "📏",
          "titulo": "Tamanho",
          "valor": "36 m²"
        },
        {
          "icon": "❄️",
          "titulo": "Climatização",
          "valor": "Ar-condicionado central"
        },
        {
          "icon": "⚡",
          "titulo": "Infraestrutura",
          "valor": "Internet de alta velocidade"
        },
        {
          "icon": "🔒",
          "titulo": "Segurança",
          "valor": "Vigilância 24/7"
        },
        {
          "icon": "🚪",
          "titulo": "Entrada",
          "valor": "Independente"
        },
        {
          "icon": "🅿️",
          "titulo": "Estacionamento",
          "valor": "Incluído"
        }
      ],
      "facilidades": [
        {
          "icon": "🅿️",
          "valor": "Estacionamento"
        },
        {
          "icon": "🛗",
          "valor": "Elevador moderno e rápido"
        },
        {
          "icon": "🏢",
          "valor": "Portaria"
        },
        {
          "icon": "🎯",
          "valor": "Localização estratégica"
        }
      ],
      "alugada": false,
      "inativa": false,
      "data_aluguel": null,
      "motivo_inativa": "",
      "destaque": false
    },
    {
      "id": 7,
      "nome": "Sala 115 - Coworking",
      "andar": "PRIMEIRO ANDAR",
      "tamanho": 28,
      "descricao": "Espaço compacto e funcional. Perfeito para profissionais autônomos e consultores.",
      "imagem_principal": "fotos_predio/foto_predio_6.jpg",
      "fotos": [
        "fotos_predio/foto_predio_6.jpg"
      ],
      "sobre": "Sobre esta Sala",
      "caracteristicas": [
        "Piso em porcelanato de alta qualidade",
        "Pintura em tons neutros e sofisticados",
        "Iluminação LED com controle de intensidade",
        "Tomadas e pontos de dados estrategicamente distribuídos",
        "Divisórias móveis para flexibilidade de layout",
        "Acabamento premium em todos os detalhes"
      ],
      "specs": [
        {
          "icon": "📏",
          "titulo": "Tamanho",
          "valor": "28 m²"
        },
        {
          "icon": "❄️",
          "titulo": "Climatização",
          "valor": "Ar-condicionado central"
        },
        {
          "icon": "⚡",
          "titulo": "Infraestrutura",
          "valor": "Internet de alta velocidade"
        },
        {
          "icon": "🔒",
          "titulo": "Segurança",
          "valor": "Vigilância 24/7"
        },
        {
          "icon": "🚪",
          "titulo": "Entrada",
          "valor": "Compartilhada"
        },
        {
          "icon": "🅿️",
          "titulo": "Estacionamento",
          "valor": "Incluído"
        }
      ],
      "facilidades": [
        {
          "icon": "🅿️",
          "valor": "Estacionamento"
        },
        {
          "icon": "🛗",
          "valor": "Elevador moderno e rápido"
        },
        {
          "icon": "🏢",
          "valor": "Portaria"
        },
        {
          "icon": "🎯",
          "valor": "Localização estratégica"
        }
      ],
      "alugada": false,
      "inativa": false,
      "data_aluguel": null,
      "motivo_inativa": "",
      "destaque": false
    },
    {
      "id": 8,
      "nome": "Loja 06 - Retail",
      "andar": "SUBSOLO",
      "tamanho": 50,
      "descricao": "Espaço versátil com bom pé-direito. Adequado para lojas de moda, acessórios ou serviços.",
      "imagem_principal": "fotos_predio/foto_predio_7.jpg",
      "fotos": [
        "fotos_predio/foto_predio_7.jpg"
      ],
      "sobre": "Sobre esta Sala",
      "caracteristicas": [
        "Piso em porcelanato de alta qualidade",
        "Pintura em tons neutros e sofisticados",
        "Iluminação LED com controle de intensidade",
        "Tomadas e pontos de dados estrategicamente distribuídos",
        "Divisórias móveis para flexibilidade de layout",
        "Acabamento premium em todos os detalhes"
      ],
      "specs": [
        {
          "icon": "📏",
          "titulo": "Tamanho",
          "valor": "50 m²"
        },
        {
          "icon": "❄️",
          "titulo": "Climatização",
          "valor": "Ar-condicionado central"
        },
        {
          "icon": "⚡",
          "titulo": "Infraestrutura",
          "valor": "Internet de alta velocidade"
        },
        {
          "icon": "🔒",
          "titulo": "Segurança",
          "valor": "Vigilância 24/7"
        },
        {
          "icon": "🚪",
          "titulo": "Entrada",
          "valor": "Independente"
        },
        {
          "icon": "🅿️",
          "titulo": "Estacionamento",
          "valor": "Incluído"
        }
      ],
      "facilidades": [
        {
          "icon": "🅿️",
          "valor": "Estacionamento"
        },
        {
          "icon": "🛗",
          "valor": "Elevador moderno e rápido"
        },
        {
          "icon": "🏢",
          "valor": "Portaria"
        },
        {
          "icon": "🎯",
          "valor": "Localização estratégica"
        }
      ],
      "alugada": false,
      "inativa": false,
      "data_aluguel": null,
      "motivo_inativa": "",
      "destaque": false
    }
  ]
}